LICENSE
asyncsqlite/__init__.py
asyncsqlite/pool.py
asyncsqlite/py.typed
asyncsqlite-0.1.7.dist-info/LICENSE
asyncsqlite-0.1.7.dist-info/WHEEL
asyncsqlite-0.1.7.dist-info/METADATA
asyncsqlite-0.1.7.dist-info/RECORD
